{"nodes": [{"node": 0, "name": "Class_0_of_1985"}, {"node": 1, "name": "Class_1_of_1985"}, {"node": 2, "name": "Class_2_of_1985"}, {"node": 3, "name": "Class_3_of_1985"}, {"node": 4, "name": "Class_4_of_1985"}, {"node": 5, "name": "Class_0_of_2000"}, {"node": 6, "name": "Class_1_of_2000"}, {"node": 7, "name": "Class_2_of_2000"}, {"node": 8, "name": "Class_3_of_2000"}, {"node": 9, "name": "Class_4_of_2000"}, {"node": 10, "name": "Class_0_of_2015"}, {"node": 11, "name": "Class_1_of_2015"}, {"node": 12, "name": "Class_2_of_2015"}, {"node": 13, "name": "Class_3_of_2015"}, {"node": 14, "name": "Class_4_of_2015"}], "links": [{"source": 0, "target": 5, "value": 45.01173918371584}, {"source": 0, "target": 6, "value": 1.9337571204275679}, {"source": 0, "target": 7, "value": 5.6101544676564}, {"source": 0, "target": 8, "value": 0.5676757825695203}, {"source": 0, "target": 9, "value": 0.01584048446292083}, {"source": 1, "target": 5, "value": 2.326509499211145}, {"source": 1, "target": 6, "value": 6.62149745156296}, {"source": 1, "target": 7, "value": 0.37272528826257284}, {"source": 1, "target": 8, "value": 0.10434809996375193}, {"source": 1, "target": 9, "value": 0.005809982760502667}, {"source": 2, "target": 5, "value": 9.837550702092768}, {"source": 2, "target": 6, "value": 0.25958473934792864}, {"source": 2, "target": 7, "value": 5.167003908393656}, {"source": 2, "target": 8, "value": 2.772365041664826}, {"source": 2, "target": 9, "value": 0.07069311693934967}, {"source": 3, "target": 5, "value": 9.231171346738835}, {"source": 3, "target": 6, "value": 0.2644799625371533}, {"source": 3, "target": 7, "value": 2.5713557827628755}, {"source": 3, "target": 8, "value": 2.223155348135897}, {"source": 3, "target": 9, "value": 0.0818018941994002}, {"source": 4, "target": 5, "value": 3.692661810079441}, {"source": 4, "target": 6, "value": 0.04963656506980855}, {"source": 4, "target": 7, "value": 1.01941892110758}, {"source": 4, "target": 8, "value": 0.1851903785678381}, {"source": 4, "target": 9, "value": 0.003873121769473337}, {"source": 5, "target": 10, "value": 57.454551234435705}, {"source": 5, "target": 11, "value": 0.3951093930971563}, {"source": 5, "target": 12, "value": 11.50812931912799}, {"source": 5, "target": 13, "value": 0.45322655216284163}, {"source": 5, "target": 14, "value": 0.28861604301439797}, {"source": 6, "target": 10, "value": 1.5036336336697198}, {"source": 6, "target": 11, "value": 6.253977159279675}, {"source": 6, "target": 12, "value": 1.3589086418488703}, {"source": 6, "target": 13, "value": 0.00856244383624948}, {"source": 6, "target": 14, "value": 0.0038739603109037126}, {"source": 7, "target": 10, "value": 8.179457163876759}, {"source": 7, "target": 11, "value": 0.059087374375884405}, {"source": 7, "target": 12, "value": 6.148888749613651}, {"source": 7, "target": 13, "value": 0.26506339080720237}, {"source": 7, "target": 14, "value": 0.08816168950958418}, {"source": 8, "target": 10, "value": 2.533468337713743}, {"source": 8, "target": 11, "value": 0.032927184918363994}, {"source": 8, "target": 12, "value": 3.1208835057101916}, {"source": 8, "target": 13, "value": 0.14573993897944396}, {"source": 8, "target": 14, "value": 0.019715683580091493}, {"source": 9, "target": 10, "value": 0.07188299040766895}, {"source": 9, "target": 11, "value": 0.0019367497139161525}, {"source": 9, "target": 12, "value": 0.07127435048257022}, {"source": 9, "target": 13, "value": 0.027114685989617835}, {"source": 9, "target": 14, "value": 0.005809823537873546}]}